f_mlx_embeddings-0.0.5.post3.dist-info/licenses/AUTHORS.rst
f_mlx_embeddings-0.0.5.post3.dist-info/licenses/LICENSE
mlx_embeddings/__init__.py
mlx_embeddings/convert.py
mlx_embeddings/tokenizer_utils.py
mlx_embeddings/utils.py
mlx_embeddings/version.py
mlx_embeddings/models/__init__.py
mlx_embeddings/models/base.py
mlx_embeddings/models/bert.py
mlx_embeddings/models/colqwen2_5.py
mlx_embeddings/models/gemma3_text.py
mlx_embeddings/models/lfm2.py
mlx_embeddings/models/modernbert.py
mlx_embeddings/models/qwen3.py
mlx_embeddings/models/siglip.py
mlx_embeddings/models/xlm_roberta.py
mlx_embeddings/tests/__init__.py
mlx_embeddings/tests/test_base.py
mlx_embeddings/tests/test_models.py
mlx_embeddings/tests/test_smoke.py
f_mlx_embeddings-0.0.5.post3.dist-info/METADATA
f_mlx_embeddings-0.0.5.post3.dist-info/WHEEL
f_mlx_embeddings-0.0.5.post3.dist-info/entry_points.txt
f_mlx_embeddings-0.0.5.post3.dist-info/top_level.txt
f_mlx_embeddings-0.0.5.post3.dist-info/RECORD
